src/__init__.py
src/__main__.py
src/main.py
src/cli/__init__.py
src/cli/__main__.py
src/cli/config_commands.py
src/cli/connection_commands.py
src/cli/data_commands.py
src/cli/main.py
src/cli/query_commands.py
src/cli/schema_commands.py
src/mcp_tools/__init__.py
src/mcp_tools/__main__.py
src/mcp_tools/create_connection_tool.py
src/mcp_tools/execute_query_tool.py
src/mcp_tools/get_schema_tool.py
src/mcp_tools/get_table_data_tool.py
src/mcp_tools/list_databases_tool.py
src/mcp_tools/mcp_server.py
src/mcp_tools/resources.py
src/models/__init__.py
src/models/__main__.py
src/models/connection.py
src/models/data.py
src/models/query.py
src/models/schema.py
src/services/__init__.py
src/services/__main__.py
src/services/connection_manager.py
src/services/data_service.py
src/services/query_executor.py
src/services/schema_service.py
sqlserver_mcp_server-1.0.0.dist-info/METADATA
sqlserver_mcp_server-1.0.0.dist-info/WHEEL
sqlserver_mcp_server-1.0.0.dist-info/entry_points.txt
sqlserver_mcp_server-1.0.0.dist-info/licenses/LICENSE
sqlserver_mcp_server-1.0.0.dist-info/RECORD
