Metadata-Version: 2.4
Name: sqlserver-mcp-server
Version: 1.0.0
Summary: A comprehensive Model Context Protocol (MCP) server for interacting with SQL Server databases
Project-URL: Homepage, https://github.com/your-org/sqlserver-mcp-server
Project-URL: Documentation, https://github.com/your-org/sqlserver-mcp-server#readme
Project-URL: Repository, https://github.com/your-org/sqlserver-mcp-server.git
Project-URL: Issues, https://github.com/your-org/sqlserver-mcp-server/issues
Project-URL: Changelog, https://github.com/your-org/sqlserver-mcp-server/blob/main/CHANGELOG.md
Project-URL: Download, https://pypi.org/project/sqlserver-mcp-server/#files
Author-email: SQL Server MCP Server Team <sqlserver-mcp@example.com>
Maintainer-email: SQL Server MCP Server Team <sqlserver-mcp@example.com>
License: GNU LESSER GENERAL PUBLIC LICENSE
License-File: LICENSE
Keywords: ai,assistant,database,mcp,model-context-protocol,odbc,protocol,pyodbc,sql-server,sqlserver
Classifier: Development Status :: 5 - Production/Stable
Classifier: Environment :: Console
Classifier: Environment :: Web Environment
Classifier: Framework :: AsyncIO
Classifier: Intended Audience :: Developers
Classifier: Intended Audience :: System Administrators
Classifier: License :: OSI Approved :: GNU Lesser General Public License v3 (LGPLv3)
Classifier: Operating System :: OS Independent
Classifier: Programming Language :: Python :: 3
Classifier: Programming Language :: Python :: 3.8
Classifier: Programming Language :: Python :: 3.9
Classifier: Programming Language :: Python :: 3.10
Classifier: Programming Language :: Python :: 3.11
Classifier: Programming Language :: Python :: 3.12
Classifier: Programming Language :: Python :: 3.13
Classifier: Topic :: Database
Classifier: Topic :: Database :: Database Engines/Servers
Classifier: Topic :: Internet :: WWW/HTTP :: HTTP Servers
Classifier: Topic :: Software Development :: Libraries :: Application Frameworks
Classifier: Topic :: Software Development :: Libraries :: Python Modules
Classifier: Topic :: System :: Networking
Requires-Python: >=3.8
Requires-Dist: click>=8.0.0
Requires-Dist: mcp>=1.0.0
Requires-Dist: pydantic>=2.0.0
Requires-Dist: pyodbc>=4.0.39
Requires-Dist: rich>=13.0.0
Requires-Dist: structlog>=23.0.0
Provides-Extra: dev
Requires-Dist: bandit>=1.7.0; extra == 'dev'
Requires-Dist: black>=23.0.0; extra == 'dev'
Requires-Dist: flake8>=6.0.0; extra == 'dev'
Requires-Dist: isort>=5.12.0; extra == 'dev'
Requires-Dist: mypy>=1.0.0; extra == 'dev'
Requires-Dist: pre-commit>=3.3.0; extra == 'dev'
Requires-Dist: pytest-asyncio>=0.21.0; extra == 'dev'
Requires-Dist: pytest-benchmark>=4.0.0; extra == 'dev'
Requires-Dist: pytest-cov>=4.0.0; extra == 'dev'
Requires-Dist: safety>=2.0.0; extra == 'dev'
Provides-Extra: docs
Requires-Dist: mkdocs-material>=9.0.0; extra == 'docs'
Requires-Dist: mkdocs>=1.4.0; extra == 'docs'
Requires-Dist: mkdocstrings>=0.20.0; extra == 'docs'
Provides-Extra: test
Requires-Dist: pytest-asyncio>=0.21.0; extra == 'test'
Requires-Dist: pytest-benchmark>=4.0.0; extra == 'test'
Requires-Dist: pytest-cov>=4.0.0; extra == 'test'
Requires-Dist: pytest-mock>=3.10.0; extra == 'test'
Requires-Dist: pytest>=7.0.0; extra == 'test'
